{
    "query": "Which methods are considered to find examples of biases and unwarranted inferences??",
    "gold_answer": "spot patterns by just looking at a collection of images, tag all descriptions with part-of-speech information, I applied Louvain clusteringLooking for adjectives marking the noun \"baby\" and also looking for most-common adjectives related to certain nouns using POS-tagging",
    "predict": "Unwarranted inferences and stereotype-driven biases.",
    "consistency": "0",
    "reasoning": "Answer A provides a detailed methodology for identifying biases and unwarranted inferences through specific techniques such as pattern recognition in images, tagging descriptions, and using clustering and part-of-speech tagging. In contrast, Answer B simply states 'unwarranted inferences and stereotype-driven biases' without elaboration on methods. While both answers relate to the topic of biases and inferences, Answer A describes methods to find them, whereas Answer B lists types of biases. Therefore, they are not semantically equivalent as they address different aspects of the query."
}